flake8_for_pycharm/__init__.py
flake8_for_pycharm/reporters.py
flake8_for_pycharm-0.4.1.data/scripts/flake8_pycharm.py
flake8_for_pycharm-0.4.1.dist-info/LICENSE
flake8_for_pycharm-0.4.1.dist-info/METADATA
flake8_for_pycharm-0.4.1.dist-info/WHEEL
flake8_for_pycharm-0.4.1.dist-info/entry_points.txt
flake8_for_pycharm-0.4.1.dist-info/top_level.txt
flake8_for_pycharm-0.4.1.dist-info/RECORD
