Metadata-Version: 2.1
Name: flake8-for-pycharm
Version: 0.4.1
Summary: Add flake8 support to pycharm. See README for how to use.
Home-page: https://gitlab.com/ramast/flake8-json
Author: Ramast Magdy
Author-email: ramast.com@gmail.com
License: MIT
Classifier: Development Status :: 5 - Production/Stable
Classifier: Environment :: Console
Classifier: Framework :: Flake8
Classifier: Intended Audience :: Developers
Classifier: License :: OSI Approved :: MIT License
Classifier: Programming Language :: Python
Classifier: Programming Language :: Python :: 3
Classifier: Programming Language :: Python :: 3.4
Classifier: Programming Language :: Python :: 3.5
Classifier: Programming Language :: Python :: 3.6
Classifier: Topic :: Software Development :: Quality Assurance
Requires-Python: >=3.4
License-File: LICENSE
